aalib.py
setup.py
python_aalib.egg-info/PKG-INFO
python_aalib.egg-info/SOURCES.txt
python_aalib.egg-info/dependency_links.txt
python_aalib.egg-info/top_level.txt