Metadata-Version: 1.0
Name: python-aalib
Version: 0.1
Summary: Bindings for AAlib
Home-page: http://jwilk.nfshost.com/software/python-aalib.html
Author: Jakub Wilk
Author-email: ubanus@users.sf.net
License: GNU GPL 2
Platform: UNKNOWN
Classifier: Development Status :: 4 - Beta
Classifier: Intended Audience :: Developers
Classifier: License :: OSI Approved :: GNU General Public License (GPL)
Classifier: Operating System :: OS Independent
Classifier: Programming Language :: Python
Classifier: Programming Language :: Python :: 2
Classifier: Topic :: Multimedia :: Graphics
